LICENSE.md
MANIFEST.in
README.md
setup.py
update_geonameszip.py
geonameszip/__init__.py
geonameszip/update.py
geonameszip.egg-info/PKG-INFO
geonameszip.egg-info/SOURCES.txt
geonameszip.egg-info/dependency_links.txt
geonameszip.egg-info/top_level.txt