Metadata-Version: 1.1
Name: geonameszip
Version: 0.3.0
Summary: Quick and dirty script/api for syncing postal codes / zip codes with a local sqlite3 database.
Home-page: https://github.com/oliverseal/python-geonameszip
Author: Oliver Wilkerson
Author-email: oliver.wilkerson@gmail.com
License: MIT
Platform: UNKNOWN
Classifier: Development Status :: 4 - Beta
Classifier: Intended Audience :: Developers
Classifier: Natural Language :: English
Classifier: License :: OSI Approved :: MIT License
Classifier: License :: Other/Proprietary License
Classifier: Operating System :: OS Independent
Classifier: Programming Language :: Python
Classifier: Programming Language :: Python :: 2
Classifier: Programming Language :: Python :: 2.6
Classifier: Programming Language :: Python :: 2.7
Classifier: Programming Language :: Python :: 3
Classifier: Programming Language :: Python :: 3.3
Classifier: Topic :: Software Development :: Libraries :: Python Modules
